README.md
setup.py
doc/config/panonrc
panon/__init__.py
panon/__main__.py
panon/config.py
panon/helper.py
panon/multiload.py
panon/shortcut.py
panon/singleton.py
panon/taskbar.py
panon.egg-info/PKG-INFO
panon.egg-info/SOURCES.txt
panon.egg-info/dependency_links.txt
panon.egg-info/entry_points.txt
panon.egg-info/requires.txt
panon.egg-info/top_level.txt
panon/glsl/__init__.py
panon/glsl/fft.glsl
panon/glsl/frag.glsl
panon/glsl/vert.glsl
panon/visualizer/__init__.py
panon/visualizer/fallback.py
panon/visualizer/glfft.py
panon/visualizer/glspectrum.py
panon/visualizer/opengl.py
panon/visualizer/source.py
panon/visualizer/spectrum.py