Metadata-Version: 1.1
Name: panon
Version: 0.1.1
Summary: A status bar for X window managers
Home-page: http://github.com/rbn42/panon
Author: rbn42
Author-email: bl100@students.waikato.ac.nz
License: MIT
Download-URL: https://github.com/rbn42/panon/archive/v0.1.1.tar.gz
Keywords: visualizer,multiload,panel,xorg
Platform: UNKNOWN
Classifier: Development Status :: 2 - Pre-Alpha
Classifier: Environment :: X11 Applications
Classifier: Intended Audience :: End Users/Desktop
Classifier: License :: OSI Approved :: GNU Affero General Public License v3
Classifier: Programming Language :: Python :: 3
